HumanTime/Durations.py
HumanTime/Holidays.py
HumanTime/Numbers.py
HumanTime/Time.py
HumanTime/Utility.py
HumanTime/Weekdays.py
HumanTime/__init__.py
HumanTime/Tools/GenerateHolidayCalendar.py
HumanTime/Tools/__init__.py
HumanTime-0.1.15.dist-info/LICENSE
HumanTime-0.1.15.dist-info/METADATA
HumanTime-0.1.15.dist-info/WHEEL
HumanTime-0.1.15.dist-info/top_level.txt
HumanTime-0.1.15.dist-info/RECORD
