Metadata-Version: 2.1
Name: HumanTime
Version: 0.1.15
Summary: Time for Humans
Home-page: https://github.com/AgalmicVentures/HumanTime
Author: Ian Hutchinson
Author-email: ihutchinson@agalmicventures.com
License: MIT
Classifier: Programming Language :: Python :: 3
Classifier: License :: OSI Approved :: MIT License
Classifier: Natural Language :: English
Classifier: Operating System :: OS Independent
Classifier: Topic :: Software Development :: Libraries
Classifier: Topic :: Utilities
License-File: LICENSE
